litex/__init__.py
litex/build/__init__.py
litex/build/dfu.py
litex/build/generic_platform.py
litex/build/generic_programmer.py
litex/build/generic_toolchain.py
litex/build/io.py
litex/build/nextpnr_wrapper.py
litex/build/openfpgaloader.py
litex/build/openocd.py
litex/build/parser.py
litex/build/tools.py
litex/build/vhd2v_converter.py
litex/build/yosys_nextpnr_toolchain.py
litex/build/yosys_wrapper.py
litex/build/altera/__init__.py
litex/build/altera/common.py
litex/build/altera/platform.py
litex/build/altera/programmer.py
litex/build/altera/quartus.py
litex/build/anlogic/__init__.py
litex/build/anlogic/anlogic.py
litex/build/anlogic/common.py
litex/build/anlogic/platform.py
litex/build/colognechip/__init__.py
litex/build/colognechip/colognechip.py
litex/build/colognechip/common.py
litex/build/colognechip/platform.py
litex/build/efinix/__init__.py
litex/build/efinix/common.py
litex/build/efinix/dbparser.py
litex/build/efinix/efinity.py
litex/build/efinix/ifacewriter.py
litex/build/efinix/ipmwriter.py
litex/build/efinix/platform.py
litex/build/efinix/programmer.py
litex/build/gowin/__init__.py
litex/build/gowin/apicula.py
litex/build/gowin/common.py
litex/build/gowin/gowin.py
litex/build/gowin/platform.py
litex/build/gowin/programmer.py
litex/build/lattice/__init__.py
litex/build/lattice/bit_to_svf.py
litex/build/lattice/common.py
litex/build/lattice/diamond.py
litex/build/lattice/icestorm.py
litex/build/lattice/oxide.py
litex/build/lattice/platform.py
litex/build/lattice/programmer.py
litex/build/lattice/radiant.py
litex/build/lattice/trellis.py
litex/build/microsemi/__init__.py
litex/build/microsemi/common.py
litex/build/microsemi/libero_soc.py
litex/build/microsemi/platform.py
litex/build/quicklogic/__init__.py
litex/build/quicklogic/common.py
litex/build/quicklogic/f4pga.py
litex/build/quicklogic/platform.py
litex/build/sim/README
litex/build/sim/__init__.py
litex/build/sim/common.py
litex/build/sim/config.py
litex/build/sim/gtkwave.py
litex/build/sim/platform.py
litex-2024.12.dist-info/licenses/LICENSE
litex-2024.12.dist-info/METADATA
litex-2024.12.dist-info/WHEEL
litex-2024.12.dist-info/entry_points.txt
litex-2024.12.dist-info/top_level.txt
litex-2024.12.dist-info/RECORD
