Metadata-Version: 2.4
Name: litex
Version: 2024.12
Summary: Python SoC/Core builder for building FPGA based systems.
Home-page: http://enjoy-digital.fr
Download-URL: https://github.com/enjoy-digital/litex
Author: Florent Kermarrec
Author-email: florent@enjoy-digital.fr
License: BSD
Keywords: HDL ASIC FPGA hardware design
Platform: Any
Classifier: Topic :: Scientific/Engineering :: Electronic Design Automation (EDA)
Classifier: Environment :: Console
Classifier: Development Status :: 3 - Alpha
Classifier: Intended Audience :: Developers
Classifier: License :: OSI Approved :: BSD License
Classifier: Operating System :: OS Independent
Classifier: Programming Language :: Python
Requires-Python: ~=3.7
License-File: LICENSE
Requires-Dist: migen
Requires-Dist: packaging
Requires-Dist: pyserial
Requires-Dist: requests
Provides-Extra: develop
Requires-Dist: mesonpexpectsetuptoolsrequests; extra == "develop"
Dynamic: author
Dynamic: author-email
Dynamic: classifier
Dynamic: description
Dynamic: description-content-type
Dynamic: download-url
Dynamic: home-page
Dynamic: keywords
Dynamic: license
Dynamic: license-file
Dynamic: platform
Dynamic: provides-extra
Dynamic: requires-dist
Dynamic: requires-python
Dynamic: summary
